pyblackbird/__init__.py
pyblackbird-0.6.dist-info/LICENSE
pyblackbird-0.6.dist-info/METADATA
pyblackbird-0.6.dist-info/WHEEL
pyblackbird-0.6.dist-info/top_level.txt
pyblackbird-0.6.dist-info/zip-safe
pyblackbird-0.6.dist-info/RECORD
