Metadata-Version: 2.1
Name: pyblackbird
Version: 0.6
Summary: Python API for talking to Monoprice Blackbird 4k 8x8 HDBaseT Matrix
Home-page: https://github.com/koolsb/pyblackbird
Download-URL: https://github.com/koolsb/pyblackbird/archive/0.5.tar.gz
Author: Ben Kools
Author-email: Ben Kools <koolsb@my.uwstout.edu>
License: MIT
Project-URL: Homepage, https://github.com/koolsb/pyblackbird
Project-URL: Bug Tracker, https://github.com/koolsb/pyblackbird/issues
Classifier: Development Status :: 4 - Beta
Classifier: Programming Language :: Python :: 3
Requires-Python: >=3.7
License-File: LICENSE
